sqbooster/__init__.py
sqbooster/databases/__init__.py
sqbooster/databases/jsonfile/__init__.py
sqbooster/databases/mongo/__init__.py
sqbooster/databases/picklefile/__init__.py
sqbooster/databases/postgresql/__init__.py
sqbooster/databases/redis/__init__.py
sqbooster/databases/sqlite/__init__.py
sqbooster/exceptions/__init__.py
sqbooster-1.0.0.dist-info/METADATA
sqbooster-1.0.0.dist-info/WHEEL
sqbooster-1.0.0.dist-info/licenses/LICENSE
sqbooster-1.0.0.dist-info/RECORD
