Metadata-Version: 2.4
Name: sqbooster
Version: 1.0.0
Summary: A python library that allows you to work with sql easily
Author-email: Ali Safamanesh <darg.q.a.a@gmail.com>
License: MIT License
License-File: LICENSE
Classifier: License :: OSI Approved :: MIT License
Classifier: Operating System :: OS Independent
Classifier: Programming Language :: Python :: 3
Requires-Python: >=3.8
